nicegui_super_extensions/__init__.py
nicegui_super_extensions/drop_file.py
nicegui_super_extensions/markdown_editor.py
nicegui_super_extensions/markdown_renderer.py
nicegui_super_extensions/reconnect_box.py
nicegui_super_extensions/reorderable.py
nicegui_super_extensions/screenshot.py
nicegui_super_extensions-0.0.3.dist-info/LICENSE
nicegui_super_extensions-0.0.3.dist-info/METADATA
nicegui_super_extensions-0.0.3.dist-info/WHEEL
nicegui_super_extensions-0.0.3.dist-info/top_level.txt
nicegui_super_extensions-0.0.3.dist-info/RECORD
