Metadata-Version: 2.1
Name: nicegui_super_extensions
Version: 0.0.3
Summary: nicegui extensions
Author-email: T2XX <antongong@foxmail.com>
Project-URL: Homepage, https://github.com/T2XX/nicegui_super_extensions
Project-URL: Issues, https://github.com/T2XX/nicegui_super_extensions/issues
Classifier: Programming Language :: Python :: 3
Classifier: License :: OSI Approved :: MIT License
Classifier: Operating System :: OS Independent
Requires-Python: >=3.8
License-File: LICENSE
